package/__init__.py
amazme-0.0.1.dist-info/LICENSE
amazme-0.0.1.dist-info/WHEEL
amazme-0.0.1.dist-info/METADATA
amazme-0.0.1.dist-info/RECORD
